openstack_health_middleware/__init__.py
openstack_health_middleware/infra_health.py
openstack_health_middleware/opts.py
openstack_health_middleware-0.20241220.0.dist-info/AUTHORS
openstack_health_middleware-0.20241220.0.dist-info/LICENSE
openstack_health_middleware-0.20241220.0.dist-info/METADATA
openstack_health_middleware-0.20241220.0.dist-info/WHEEL
openstack_health_middleware-0.20241220.0.dist-info/entry_points.txt
openstack_health_middleware-0.20241220.0.dist-info/pbr.json
openstack_health_middleware-0.20241220.0.dist-info/top_level.txt
openstack_health_middleware-0.20241220.0.dist-info/RECORD
